miniadmin/__init__.py
miniadmin/admin.py
miniagent/__init__.py
miniagent/adapter.py
miniagent/app_config.py
miniagent/command_receiver.py
miniagent/common.py
miniagent/event_receiver.py
miniagent/event_sender.py
miniagent/executer.py
miniagent/flask_zipkin.py
miniagent/job_receiver.py
miniagent/message_receiver.py
miniagent/message_sender.py
miniagent/models.py
miniagent/prework.py
miniagent/adapters/__init__.py
miniagent/adapters/kafka_producer.py
miniagent/adapters/opensearch_caller.py
miniagent/adapters/rest_caller.py
miniagent-0.0.28.dist-info/LICENSE
miniagent-0.0.28.dist-info/METADATA
miniagent-0.0.28.dist-info/WHEEL
miniagent-0.0.28.dist-info/entry_points.txt
miniagent-0.0.28.dist-info/top_level.txt
miniagent-0.0.28.dist-info/RECORD
