Metadata-Version: 2.1
Name: miniagent
Version: 0.0.28
Summary: Multi-adaptable and lightweight server framework based on Flask
Home-page: https://github.com/tanminkwan/local-agent
Author: tanminkwan
Author-email: tanminkwan@gmail.com
License: MIT
Keywords: flask,sqlalchemy,scheduler,zipkin,kafka
Classifier: Programming Language :: Python :: 3.9
Classifier: Programming Language :: Python :: 3.10
Requires-Python: >=3.9
License-File: LICENSE
Requires-Dist: aniso8601 (>=9.0.1)
Requires-Dist: APScheduler (>=3.10.1)
Requires-Dist: blinker (>=1.6.2)
Requires-Dist: certifi (>=2022.12.7)
Requires-Dist: charset-normalizer (>=3.1.0)
Requires-Dist: click (>=8.1.3)
Requires-Dist: Flask (>=2.3.1)
Requires-Dist: Flask-API (>=3.0.post1)
Requires-Dist: Flask-APScheduler (>=1.12.4)
Requires-Dist: Flask-Cors (>=3.0.10)
Requires-Dist: Flask-RESTful (>=0.3.9)
Requires-Dist: Flask-SQLAlchemy (>=3.0.3)
Requires-Dist: greenlet (>=2.0.2)
Requires-Dist: idna (>=3.4)
Requires-Dist: itsdangerous (>=2.1.2)
Requires-Dist: Jinja2 (>=3.1.2)
Requires-Dist: kafka-python (>=2.0.2)
Requires-Dist: MarkupSafe (>=2.1.2)
Requires-Dist: polling2 (>=0.5.0)
Requires-Dist: python-dateutil (>=2.8.2)
Requires-Dist: pytz (>=2023.3)
Requires-Dist: pytz-deprecation-shim (>=0.1.0.post0)
Requires-Dist: requests (>=2.29.0)
Requires-Dist: six (>=1.16.0)
Requires-Dist: SQLAlchemy (>=2.0.11)
Requires-Dist: typing-extensions (>=4.5.0)
Requires-Dist: tzdata (>=2023.3)
Requires-Dist: tzlocal (>=4.3)
Requires-Dist: urllib3 (>=1.26.15)
Requires-Dist: Werkzeug (>=2.3.2)
Requires-Dist: PyGithub (>=1.58.1)
Requires-Dist: py-zipkin (>=1.2.8)
Requires-Dist: opensearch-py (>=2.2.0)
